{
    "id": "014891",
    "subject": "THPERF",
    "catalogNumber": "378",
    "title": "Race and Performance",
    "description": "This course explores the ways critical race and performance studies can help us understand English language-based performance in the 20th and 21st centuries. Close attention is paid to the primary historical, political, and cultural contexts that inform the creation, development, and presentation of performance works.",
    "term": [
        "Fall"
    ],
    "prereq": [],
    "coreq": [],
    "antireq": [],
    "next": []
}