{
    "id": "012650",
    "subject": "CT",
    "catalogNumber": "615",
    "title": "Catholic Social Ethics",
    "description": "A study of the basic principlies of Catholic social teaching through an examination of church documents and the rise of social movements.  Exploration of contemporary applications of the basic principles to issues such as poverty, immigration, the market economy, women, agriculture, ecology, work.",
    "term": [],
    "prereq": [],
    "coreq": [],
    "antireq": [],
    "next": []
}