{
    "id": "011635",
    "subject": "RS",
    "catalogNumber": "211",
    "title": "Jewish Responses to the Holocaust",
    "description": "The catastrophe and devastation of the Holocaust and the radical nature of its evil demanded responses within contemporary Jewish thought, identity, and experience. This course will explore philosophical, theological (Jewish law, rabbinic), literary (novels, poetry, memoirs, plays), and artistic (museums, memorials) attempts to deal with the issues the Holocaust raises. [Note: This course fulfils an Area 1 requirement for Religious Studies majors.]",
    "term": [
        "Winter"
    ],
    "prereq": [],
    "coreq": [],
    "antireq": [],
    "next": []
}