{
    "id": "008324",
    "subject": "RS",
    "catalogNumber": "254",
    "title": "Christian Sexual Ethics",
    "description": "Historical and contemporary Christian approaches to ethical questions about human sexuality and relationships. Topics include marriage, celibacy, single life, homosexuality, HIV/AIDS, sexual violence, gender roles, abortion, reproductive technologies, and sexuality and spirituality. [Note: This course fulfils an Area 2 requirement for Religious Studies majors.]",
    "term": [],
    "prereq": [],
    "coreq": [],
    "antireq": [],
    "next": []
}