{
    "id": "016088",
    "subject": "RS",
    "catalogNumber": "264",
    "title": "Spiritual Journeys",
    "description": "An examination of spiritual autobiographies, attending to themes such as context, conversion, the relationship of individual and community, the dynamic character of spiritual identity, and self-presentation. This course may consider the writings of persons such as Augustine, Dorothy Day, Malcolm X, Elie Wiesel, Mother Teresa, Martin Luther King Jr., and the Dalai Lama, among others.",
    "term": [],
    "prereq": [],
    "coreq": [],
    "antireq": [],
    "next": []
}