{
    "id": "012739",
    "subject": "GSJ",
    "catalogNumber": "320",
    "title": "Sex and the World Religions",
    "description": "This course examines deeply rooted attitudes in the major world religions toward sexual identity, practices, and gender. Examining sacred scriptures and codes of conduct from the world religions, as well as fictional writings and films, this course enables students to explore various social and religious traditions. [Note: This course fulfils an Area 1 requirement for Religious Studies majors.]",
    "term": [],
    "prereq": [],
    "coreq": [],
    "antireq": [
        "WS 320"
    ],
    "next": []
}