{
    "id": "014863",
    "subject": "BME",
    "catalogNumber": "401",
    "title": "Seminar",
    "description": "Biomedical engineering fourth-year students will meet with a faculty member designated as their class professor. Performance in assignments, conceptual difficulties with courses, interrelation of coursework, later work, and engineering practice will be discussed. Non-credit course. [Offered: F]",
    "term": [
        "Fall"
    ],
    "prereq": [],
    "coreq": [],
    "antireq": [],
    "next": []
}