{
    "id": "011009",
    "subject": "PACS",
    "catalogNumber": "324",
    "title": "Human Rights, Peace, and Business",
    "description": "This course will explore the tension between the values of human security/human rights and traditional economic policy. The impact of this dynamic relationship on the well-being of individuals as well as on corporations and international economic institutions to promote peace and just development will also be analyzed.",
    "term": [],
    "prereq": [],
    "coreq": [],
    "antireq": [],
    "next": []
}