{
    "id": "011979",
    "subject": "SWREN",
    "catalogNumber": "312R",
    "title": "Homelessness and Public Policy",
    "description": "This course provides students with a basic overview of homelessness in modern society. Its goal is to familiarize students with the human, social, political and economic aspects of homelessness. Throughout, the emphasis will be on understanding homelessness from a public policy framework - its incidence and prevalence, etiology, consequences, and strategies for its prevention and amelioration. [Note: SWREN 312R is available only to students who have been given conditional admission to the BSW program; such students must have already completed their first undergraduate degree.]",
    "term": [
        "Winter"
    ],
    "prereq": [],
    "coreq": [],
    "antireq": [],
    "next": []
}