{
    "id": "016307",
    "subject": "SFM",
    "catalogNumber": "401",
    "title": "Social and Human Capital Accounting",
    "description": "This course examines approaches and methodologies used by firms to understand and measure the value added by social and human capital, to assess positive and negative impacts, and to provide information for decision-making that informs and influences external and internal stakeholders.",
    "term": [],
    "prereq": [],
    "coreq": [],
    "antireq": [],
    "next": []
}