{
    "id": "013266",
    "subject": "GBDA",
    "catalogNumber": "306",
    "title": "Ethics and Values in Design",
    "description": "This course will explore the ethical responsibilities that emerge from the nexus of design, business, and globalization. Students will critically reflect upon the ethical considerations behind contemporary business and design practices. [Note: Offered at Stratford campus.]",
    "term": [
        "Winter"
    ],
    "prereq": [],
    "coreq": [],
    "antireq": [],
    "next": []
}