{
    "id": "015077",
    "subject": "SPAN",
    "catalogNumber": "395",
    "title": "Cultural Dimensions in English/Spanish Literary Translation",
    "description": "This course focuses on the actual practice of translating literature, not only as the transformation of textual expressions, but also as a process of cultural interpretation. Besides reinforcing vocabulary and grammar, students will also review and research notions of different literary genres (poetry, narrative, and theatre), and solidify their knowledge of cultural studies.",
    "term": [],
    "prereq": [
        "SPAN 301A"
    ],
    "coreq": [],
    "antireq": [],
    "next": []
}