{
    "id": "006576",
    "subject": "KIN",
    "catalogNumber": "357",
    "title": "Motor Learning and Neuroplasticity",
    "description": "This course will examine the neural control of movement and how experience shapes brain reorganization to support skilled motor ability. Evidence from behavioural and neuroimaging studies will be considered with an emphasis on leveraging principles of motor learning to skill acquisition and skilled performance in sport/occupational environments and the rehabilitation of movement disorders/injuries.",
    "term": [
        "Fall"
    ],
    "prereq": [
        "KIN 255"
    ],
    "coreq": [],
    "antireq": [],
    "next": []
}