{
    "id": "016327",
    "subject": "NANO",
    "catalogNumber": "603",
    "title": "Nanocomposites",
    "description": "Introduction to nanomaterials and nanocomposites relevant to advanced manufacturing, transportation, energy, environmental and packaging applications. Nanocomposites in nature. Dispersion, mixing of nanoparticles and liquids, percolation theory. Polymer nanocomposite manufacturing approaches and modification of nanoparticles for controlled functionality. Nanostructures and models for mechanical, electrical, thermal and gas diffusion properties in nanocomposites. Biobased nanoparticles and nanocomposite. Nanofibers. Health and safety of nanocomposites. Selected Research Topics and Patents Seminars and Assessments.",
    "term": [
        "Spring"
    ],
    "prereq": [],
    "coreq": [],
    "antireq": [
        "NANO 701",
        "NANO 702"
    ],
    "next": []
}