{
    "id": "013999",
    "subject": "EASIA",
    "catalogNumber": "202R",
    "title": "Chinese Culture and Society",
    "description": "The course explores the interface of tradition and modernity in Chinese life. Topics include traditional and modern Chinese culture, language, education, art, technology, and business. [Note: Formerly CHINA 272R.]",
    "term": [
        "Fall",
        "Winter",
        "Spring"
    ],
    "prereq": [],
    "coreq": [],
    "antireq": [
        "EASIA 202R",
        "CHINA 272R"
    ],
    "next": []
}