{
    "id": "015694",
    "subject": "CDNST",
    "catalogNumber": "212",
    "title": "Narratives of Canadian Identity",
    "description": "A multidisciplinary examination of alternative narratives of Canadian identity. Drawing on essays, literature, film, and art, students will explore the perennial question of what it means to be Canadian and examine the factors that have driven different answers to that question over time.",
    "term": [],
    "prereq": [],
    "coreq": [],
    "antireq": [],
    "next": []
}