{
    "id": "015348",
    "subject": "AE",
    "catalogNumber": "491",
    "title": "Engineering Law and Ethics",
    "description": "Background (Charter of Rights and Freedoms), contracts, torts (negligent malpractice), forms of carrying on business, professional practice (Professional Engineers Act, joint practice rules, professional misconduct and sexual harassment), alternate dispute resolution, construction liens, intellectual property (patents, trade marks, copyrights and industrial designs), labour relations and employment law, environmental law. [Offered: S]",
    "term": [
        "Spring"
    ],
    "prereq": [],
    "coreq": [],
    "antireq": [
        "CIVE 491"
    ],
    "next": []
}