{
    "id": "013458",
    "subject": "KIN",
    "catalogNumber": "654",
    "title": "Instrumentation in Neuroscience Research",
    "description": "Human neuroscience research techniques are discussed in class and used in laboratory sessions.  Students will learn the theory and gain practical experience with electroencephalography, event-related potentials, functional magnetic resonance imaging, transcranial magnetic stimulation, electromyography, digitized optical tacking of movement, psychophysics and survey methodologies.",
    "term": [
        "Winter"
    ],
    "prereq": [],
    "coreq": [],
    "antireq": [],
    "next": []
}