{
    "id": "007018",
    "subject": "MUSIC",
    "catalogNumber": "270",
    "title": "Music Theory 1",
    "description": "The study of basic melodic, harmonic, and voice leading concepts including an introduction to figured bass and functional harmony. Ear-training, sight-singing, and keyboard lab sessions will be integrated with written and analytical work. [Note: A basic knowledge of scales, triads, and music notation is required.]",
    "term": [
        "Fall",
        "Winter",
        "Spring"
    ],
    "prereq": [],
    "coreq": [],
    "antireq": [],
    "next": [
        "MUSIC 222",
        "MUSIC 271"
    ]
}