{
    "id": "006888",
    "subject": "MATH",
    "catalogNumber": "147",
    "title": "Calculus 1 (Advanced Level)",
    "description": "MATH 147 is an advanced-level version of MATH 137. [Offered: F]",
    "term": [
        "Fall"
    ],
    "prereq": [],
    "coreq": [],
    "antireq": [
        "MATH 116",
        "MATH 117",
        "MATH 124",
        "MATH 127",
        "MATH 137"
    ],
    "next": [
        "ACTSC 231",
        "MATH 118",
        "MATH 119",
        "MATH 128",
        "MATH 138",
        "MATH 148",
        "STAT 230",
        "STAT 240",
        "BIOL 364",
        "PHYS 175",
        "PHYS 225",
        "PMATH 320",
        "PMATH 321"
    ]
}