{
    "id": "005150",
    "subject": "ENGL",
    "catalogNumber": "318",
    "title": "Contemporary Canadian Literature",
    "description": "This course examines Canadian Literature written in the latter decades of the 20th century and into the 21st century. Literary works are studied in relation to relevant contemporary social, cultural and political topics, such as nationalism, indigeneity, multiculturalism, and diaspora.",
    "term": [],
    "prereq": [],
    "coreq": [],
    "antireq": [],
    "next": []
}