{
    "id": "005168",
    "subject": "ENGL",
    "catalogNumber": "365",
    "title": "Selected Studies",
    "description": "Designed to provide an in-depth study of problems and/or authors selected by the instructor. Students interested in initiating such courses are encouraged to do so by bringing their ideas to the attention of individual instructors.",
    "term": [
        "Fall",
        "Winter",
        "Spring"
    ],
    "prereq": [],
    "coreq": [],
    "antireq": [],
    "next": []
}