{
    "id": "007807",
    "subject": "PSCI",
    "catalogNumber": "391",
    "title": "Special Studies",
    "description": "Course topics vary. Students wishing to study a topic of a particular interest may consult with the department's undergraduate officer about the requirements of a reading course. Past examples include political economy of energy in Canada, and dynastic politics in Pakistan. [Note: This is a repeatable course, subject to different content; it may be completed a total of two times.]",
    "term": [
        "Fall",
        "Winter",
        "Spring"
    ],
    "prereq": [],
    "coreq": [],
    "antireq": [],
    "next": []
}