{
    "id": "007913",
    "subject": "PSYCH",
    "catalogNumber": "231",
    "title": "The Psychology of Religious Experience",
    "description": "Approaches of traditional psychological theories toward phenomena of religious experience, mysticism, and prayer are examined. The psychological process of creating and naming \"gods\" is considered as well as comparisons among altered states of consciousness including some forms of prayer.",
    "term": [
        "Fall"
    ],
    "prereq": [
        "PSYCH 101",
        "PSYCH 101R"
    ],
    "coreq": [],
    "antireq": [],
    "next": []
}