{
    "id": "007939",
    "subject": "PSYCH",
    "catalogNumber": "307",
    "title": "Human Neuropsychology",
    "description": "An introduction to current human experimental neuropsychology. The course will review evidence for brain-behaviour interactions obtained from studies of human brain damage and from investigations of the normal brain. Topics such as the representation of language, hemispheric specialization, memory, spatial ability, dyslexia, movement disorders, and affective disorders will be considered.",
    "term": [
        "Fall"
    ],
    "prereq": [
        "PSYCH 207",
        "PSYCH 261",
        "KIN 356"
    ],
    "coreq": [],
    "antireq": [],
    "next": []
}