{
    "id": "002764",
    "subject": "PSYCH",
    "catalogNumber": "776",
    "title": "Problem Solving, Judgment and  Decision-Making",
    "description": "A seminar on the cognitive processes involved in problem solving, judgment and decision making. Representative topics include reasoning, traditional and artificial intelligence approaches to problem solving, heuristics and biases in judgment, and theories of choice behaviour.",
    "term": [],
    "prereq": [],
    "coreq": [],
    "antireq": [],
    "next": []
}