{
    "id": "000512",
    "subject": "CIVE",
    "catalogNumber": "670",
    "title": "Physico-Chemical Processes of Water and Wastewater Treatment",
    "description": "Principles and design of physico-chemical processes for effecting water quality transformations in water. Process dynamics, reactions and reactors. Filtration, coagulation, flocculation adsorption and ion exchange. Membrane processes including reverse osmosis, electrodialysis and ultrafiltration. Principles of aeration and gas transfer, disinfection solid liquid separation and sludge handling.",
    "term": [
        "Winter"
    ],
    "prereq": [],
    "coreq": [],
    "antireq": [],
    "next": []
}