{
    "id": "015211",
    "subject": "NE",
    "catalogNumber": "450",
    "title": "Work-term Report 3",
    "description": "An engineering report based upon a technical project, activity, or analysis carried out by the student, normally during work-term employment following the 3B academic term. Evaluation is based upon a level of written communication, technical proficiency, and engineering analysis appropriate to a fourth-year engineering student. [Offered: W]",
    "term": [
        "Winter"
    ],
    "prereq": [],
    "coreq": [],
    "antireq": [
        "MSCI 491",
        "WKRPT 400",
        "WKRPT 401"
    ],
    "next": []
}