{
    "id": "012237",
    "subject": "NE",
    "catalogNumber": "222",
    "title": "Organic Chemistry for Nanotechnology Engineers",
    "description": "Nomenclature, stereochemistry and reactions of important classes of organic compounds. Reaction mechanisms and energetics. Aromaticity and simple molecular orbital theory of conjugated systems. Applications to nanomaterials and/or devices. [Offered: F]",
    "term": [
        "Fall"
    ],
    "prereq": [],
    "coreq": [],
    "antireq": [
        "CHEM 262",
        "CHEM 262L",
        "CHEM 264",
        "CHEM 266",
        "CHEM 266L"
    ],
    "next": [
        "CHEM 267"
    ]
}