{
    "id": "003746",
    "subject": "BIOL",
    "catalogNumber": "457",
    "title": "Analysis of Communities",
    "description": "A study of the organization, structure and development of communities with emphasis on vegetation change. Topics include: diversity, stability; succession; sampling procedures and multivariate analysis. [Offered: W]",
    "term": [
        "Winter"
    ],
    "prereq": [
        "BIOL 150",
        "BIOL 250",
        "ENVS 200",
        "STAT 202",
        "ECON 221",
        "ENVS 278"
    ],
    "coreq": [],
    "antireq": [],
    "next": []
}