{
    "id": "015541",
    "subject": "ITALST",
    "catalogNumber": "265",
    "title": "The Mafia",
    "description": "This course analyzes the visual media representation of the Mafia in North America and the manner in which it often glorifies the Italian Mafiosi's lifestyle. The goal is to deconstruct the romanticized portrayal of the Italian and Italian-American gangster created in visual media by analyzing atrocities committed by organized crime.",
    "term": [
        "Fall",
        "Spring"
    ],
    "prereq": [],
    "coreq": [],
    "antireq": [
        "ITALST 396"
    ],
    "next": []
}