{
    "id": "007479",
    "subject": "PHYS",
    "catalogNumber": "475",
    "title": "Cosmology",
    "description": "Robertson-Walker metric and Friedmann equations.  Observational cosmology.  Dark matter and dark energy.  Gravitational lensing. Big Bang nucleosynthesis, the cosmic microwave background.  Inflation.  Structure formation. [Note:  PHYS 474 is recommended.  Offered: F]",
    "term": [
        "Fall"
    ],
    "prereq": [
        "AMATH 261",
        "AMATH 271",
        "PHYS 263"
    ],
    "coreq": [],
    "antireq": [],
    "next": []
}