{
    "id": "003969",
    "subject": "CHE",
    "catalogNumber": "483",
    "title": "Group Design Project and Symposium",
    "description": "Completion of the design project cycle started in CHE 482 and communication of the engineering design work. Submission of a written final report. Lecture-style technical presentation by group members. Poster-style technical presentation with group members available to discuss the project. [Offered: W]",
    "term": [
        "Winter"
    ],
    "prereq": [
        "CHE 482"
    ],
    "coreq": [],
    "antireq": [],
    "next": []
}