{
    "id": "013080",
    "subject": "BET",
    "catalogNumber": "600",
    "title": "Applied Business Leadership Skills for Entrepreneurs",
    "description": "The course provides students with the opportunity to develop a range of soft skills and the business acumen necessary to maximize the likelihood of success in an entrepreneurial environment.  Topics include communication and interpersonal skills, leadership, and negotiation skills.  A range of applied approaches are used, including integrated cases, simulations, and interaction with the local business community.  Most activities are team based.",
    "term": [
        "Fall",
        "Winter"
    ],
    "prereq": [],
    "coreq": [],
    "antireq": [],
    "next": []
}