{
    "id": "012909",
    "subject": "BIOL",
    "catalogNumber": "462",
    "title": "Applied Wetland Science",
    "description": "Advanced concepts on wetland ecosystems in the context of regional and global earth systems processes such as carbon and nitrogen cycling and climate change, applications of wetland paleoecology, use of isotopes and other geochemical tools in wetland science, and wetland engineering in landscape rehabilitation and ecotechnology. Current issues in Canada and abroad will be examined. [Offered: F]",
    "term": [
        "Fall"
    ],
    "prereq": [
        "EARTH 221",
        "EARTH 322",
        "EARTH 358",
        "BIOL 350",
        "BIOL 351",
        "ENVE 375",
        "ENVE 376"
    ],
    "coreq": [],
    "antireq": [
        "GEOG 405"
    ],
    "next": []
}