{
    "id": "000174",
    "subject": "BIOL",
    "catalogNumber": "618",
    "title": "Advanced Microbial Physiology",
    "description": "Discussion of current advances in selected topics in physiology of prokaryotic and/or eukaryotic microorganisms. Recently published research results will be the central points for the discussion. The topics might include but are not limited to microbiol growth behaviour under extreme conditions, microbial roles in the cycles of specific elements, processes of energy conservation, and properties and functions of key enzymes in microbial metabolic pathways.",
    "term": [
        "Fall"
    ],
    "prereq": [],
    "coreq": [],
    "antireq": [],
    "next": []
}